[
	{
		"label": 0,
		"opcode": "EQUN",
		"flag": 1,
		"fixed_param": [
			20
		],
		"raw_args": "97650100"
	},
	{
		"label": 10,
		"opcode": "BGM",
		"flag": 1,
		"fixed_param": [
			31
		],
		"raw_args": "b1860100"
	},
	{
		"label": 20,
		"opcode": "FLAGCLR",
		"flag": 1,
		"fixed_param": [
			34
		],
		"raw_args": "bc17da180000"
	},
	{
		"label": 32,
		"opcode": "FLAGCLR",
		"flag": 0,
		"fixed_param": [],
		"raw_args": "35016e010000"
	},
	{
		"label": 42,
		"opcode": "EQUN",
		"flag": 0,
		"fixed_param": [],
		"raw_args": "d3030000"
	},
	{
		"label": 50,
		"opcode": "EQUN",
		"flag": 1,
		"fixed_param": [
			37
		],
		"raw_args": "18180700"
	},
	{
		"label": 60,
		"opcode": "EQUN",
		"flag": 0,
		"fixed_param": [],
		"raw_args": "19180000"
	},
	{
		"label": 68,
		"opcode": "CLOSE_WINDOW",
		"flag": 0,
		"fixed_param": [],
		"raw_args": ""
	},
	{
		"label": 72,
		"opcode": "TASK",
		"flag": 0,
		"fixed_param": [],
		"task_type": 21,
		"raw_args": "15000100"
	},
	{
		"label": 80,
		"opcode": "EQUN",
		"flag": 1,
		"fixed_param": [
			38
		],
		"raw_args": "01000000"
	},
	{
		"label": 90,
		"opcode": "EQUN",
		"flag": 1,
		"fixed_param": [
			48
		],
		"raw_args": "97650100"
	},
	{
		"label": 100,
		"opcode": "EQUN",
		"flag": 1,
		"fixed_param": [
			61
		],
		"raw_args": "2b4e0700"
	},
	{
		"label": 110,
		"opcode": "EQUN",
		"flag": 1,
		"fixed_param": [
			62
		],
		"raw_args": "2c4e0000"
	},
	{
		"label": 120,
		"opcode": "FARCALL",
		"flag": 1,
		"fixed_param": [
			65
		],
		"index": 0,
		"filename": "seen8540",
		"jump_pos": 0,
		"end": "2332303031310023323030313200"
	},
	{
		"label": 156,
		"opcode": "EQUN",
		"flag": 1,
		"fixed_param": [
			66
		],
		"raw_args": "45010100"
	},
	{
		"label": 166,
		"opcode": "EQUN",
		"flag": 1,
		"fixed_param": [
			67
		],
		"raw_args": "46010000"
	},
	{
		"label": 176,
		"opcode": "EQUN",
		"flag": 1,
		"fixed_param": [
			68
		],
		"raw_args": "3c010100"
	},
	{
		"label": 186,
		"opcode": "FARCALL",
		"flag": 1,
		"fixed_param": [
			69
		],
		"index": 1,
		"filename": "seen8540",
		"jump_pos": 7380,
		"end": "300030003000"
	},
	{
		"label": 214,
		"opcode": "EQUN",
		"flag": 1,
		"fixed_param": [
			71
		],
		"raw_args": "87180000"
	},
	{
		"label": 224,
		"opcode": "EQUN",
		"flag": 0,
		"fixed_param": [],
		"raw_args": "4a010000"
	},
	{
		"label": 232,
		"opcode": "EQUN",
		"flag": 0,
		"fixed_param": [],
		"raw_args": "e41f5d00"
	},
	{
		"label": 240,
		"opcode": "EQUN",
		"flag": 0,
		"fixed_param": [],
		"raw_args": "e51f6d00"
	},
	{
		"label": 248,
		"opcode": "FARCALL",
		"flag": 1,
		"fixed_param": [
			72
		],
		"index": 2,
		"filename": "seen8540",
		"jump_pos": 8118,
		"end": null
	},
	{
		"label": 270,
		"opcode": "BTFUNC",
		"flag": 1,
		"fixed_param": [
			73
		],
		"raw_args": "00006600000018181918"
	},
	{
		"label": 286,
		"opcode": "EQUN",
		"flag": 0,
		"fixed_param": [],
		"raw_args": "47010000"
	},
	{
		"label": 294,
		"opcode": "EQUN",
		"flag": 0,
		"fixed_param": [],
		"raw_args": "70180000"
	},
	{
		"label": 302,
		"opcode": "BTFUNC",
		"flag": 0,
		"fixed_param": [],
		"raw_args": "00006600010019181818"
	},
	{
		"label": 316,
		"opcode": "EQUN",
		"flag": 0,
		"fixed_param": [],
		"raw_args": "48010000"
	},
	{
		"label": 324,
		"opcode": "EQUN",
		"flag": 0,
		"fixed_param": [],
		"raw_args": "71180000"
	},
	{
		"label": 332,
		"opcode": "FARCALL",
		"flag": 1,
		"fixed_param": [
			74
		],
		"index": 3,
		"filename": "seen8540",
		"jump_pos": 8286,
		"end": null
	},
	{
		"label": 354,
		"opcode": "EQUN",
		"flag": 1,
		"fixed_param": [
			75
		],
		"raw_args": "0718ffff"
	},
	{
		"label": 364,
		"opcode": "EQUN",
		"flag": 0,
		"fixed_param": [],
		"raw_args": "08180000"
	},
	{
		"label": 372,
		"opcode": "EQUN",
		"flag": 1,
		"fixed_param": [
			76
		],
		"raw_args": "52180000"
	},
	{
		"label": 382,
		"opcode": "EQUN",
		"flag": 0,
		"fixed_param": [],
		"raw_args": "53180100"
	},
	{
		"label": 390,
		"opcode": "EQUN",
		"flag": 1,
		"fixed_param": [
			77
		],
		"raw_args": "17181800"
	},
	{
		"label": 400,
		"opcode": "EQUN",
		"flag": 1,
		"fixed_param": [
			78
		],
		"raw_args": "38010000"
	},
	{
		"label": 410,
		"opcode": "EQUN",
		"flag": 1,
		"fixed_param": [
			79
		],
		"raw_args": "35010000"
	},
	{
		"label": 420,
		"opcode": "EQUN",
		"flag": 1,
		"fixed_param": [
			80
		],
		"raw_args": "d81f0000"
	},
	{
		"label": 430,
		"opcode": "EQUN",
		"flag": 0,
		"fixed_param": [],
		"raw_args": "da1f0000"
	},
	{
		"label": 438,
		"opcode": "EQUN",
		"flag": 0,
		"fixed_param": [],
		"raw_args": "dc1f0000"
	},
	{
		"label": 446,
		"opcode": "EQUN",
		"flag": 0,
		"fixed_param": [],
		"raw_args": "de1f0000"
	},
	{
		"label": 454,
		"opcode": "EQUN",
		"flag": 0,
		"fixed_param": [],
		"raw_args": "e01f0000"
	},
	{
		"label": 462,
		"opcode": "EQUN",
		"flag": 0,
		"fixed_param": [],
		"raw_args": "d91f0000"
	},
	{
		"label": 470,
		"opcode": "EQUN",
		"flag": 0,
		"fixed_param": [],
		"raw_args": "db1f0000"
	},
	{
		"label": 478,
		"opcode": "EQUN",
		"flag": 0,
		"fixed_param": [],
		"raw_args": "dd1f0000"
	},
	{
		"label": 486,
		"opcode": "EQUN",
		"flag": 0,
		"fixed_param": [],
		"raw_args": "df1f0000"
	},
	{
		"label": 494,
		"opcode": "EQUN",
		"flag": 0,
		"fixed_param": [],
		"raw_args": "e11f0000"
	},
	{
		"label": 502,
		"opcode": "EQUN",
		"flag": 1,
		"fixed_param": [
			81
		],
		"raw_args": "1a180000"
	},
	{
		"label": 512,
		"opcode": "EQUN",
		"flag": 0,
		"fixed_param": [],
		"raw_args": "1c180000"
	},
	{
		"label": 520,
		"opcode": "EQUN",
		"flag": 0,
		"fixed_param": [],
		"raw_args": "1e180000"
	},
	{
		"label": 528,
		"opcode": "EQUN",
		"flag": 0,
		"fixed_param": [],
		"raw_args": "1b180000"
	},
	{
		"label": 536,
		"opcode": "EQUN",
		"flag": 0,
		"fixed_param": [],
		"raw_args": "1d180000"
	},
	{
		"label": 544,
		"opcode": "EQUN",
		"flag": 0,
		"fixed_param": [],
		"raw_args": "1f180000"
	},
	{
		"label": 552,
		"opcode": "EQUN",
		"flag": 1,
		"fixed_param": [
			82
		],
		"raw_args": "5b570000"
	},
	{
		"label": 562,
		"opcode": "EQUN",
		"flag": 0,
		"fixed_param": [],
		"raw_args": "62180000"
	},
	{
		"label": 570,
		"opcode": "EQUN",
		"flag": 0,
		"fixed_param": [],
		"raw_args": "5c180000"
	},
	{
		"label": 578,
		"opcode": "EQUN",
		"flag": 0,
		"fixed_param": [],
		"raw_args": "5e180000"
	},
	{
		"label": 586,
		"opcode": "EQUN",
		"flag": 0,
		"fixed_param": [],
		"raw_args": "83180000"
	},
	{
		"label": 594,
		"opcode": "EQUN",
		"flag": 0,
		"fixed_param": [],
		"raw_args": "85180000"
	},
	{
		"label": 602,
		"opcode": "EQUN",
		"flag": 0,
		"fixed_param": [],
		"raw_args": "5c570000"
	},
	{
		"label": 610,
		"opcode": "EQUN",
		"flag": 0,
		"fixed_param": [],
		"raw_args": "63180000"
	},
	{
		"label": 618,
		"opcode": "EQUN",
		"flag": 0,
		"fixed_param": [],
		"raw_args": "5d180000"
	},
	{
		"label": 626,
		"opcode": "EQUN",
		"flag": 0,
		"fixed_param": [],
		"raw_args": "5f180000"
	},
	{
		"label": 634,
		"opcode": "EQUN",
		"flag": 0,
		"fixed_param": [],
		"raw_args": "84180000"
	},
	{
		"label": 642,
		"opcode": "EQUN",
		"flag": 0,
		"fixed_param": [],
		"raw_args": "86180000"
	},
	{
		"label": 650,
		"opcode": "EQUN",
		"flag": 1,
		"fixed_param": [
			83
		],
		"raw_args": "3a010000"
	},
	{
		"label": 660,
		"opcode": "EQUN",
		"flag": 0,
		"fixed_param": [],
		"raw_args": "60180000"
	},
	{
		"label": 668,
		"opcode": "EQUN",
		"flag": 0,
		"fixed_param": [],
		"raw_args": "7b180000"
	},
	{
		"label": 676,
		"opcode": "EQUN",
		"flag": 0,
		"fixed_param": [],
		"raw_args": "36010000"
	},
	{
		"label": 684,
		"opcode": "EQUN",
		"flag": 0,
		"fixed_param": [],
		"raw_args": "3b010000"
	},
	{
		"label": 692,
		"opcode": "EQUN",
		"flag": 0,
		"fixed_param": [],
		"raw_args": "61180000"
	},
	{
		"label": 700,
		"opcode": "EQUN",
		"flag": 0,
		"fixed_param": [],
		"raw_args": "7c180000"
	},
	{
		"label": 708,
		"opcode": "EQUN",
		"flag": 0,
		"fixed_param": [],
		"raw_args": "37010000"
	},
	{
		"label": 716,
		"opcode": "EQUN",
		"flag": 1,
		"fixed_param": [
			84
		],
		"raw_args": "74180000"
	},
	{
		"label": 726,
		"opcode": "EQUN",
		"flag": 0,
		"fixed_param": [],
		"raw_args": "75180000"
	},
	{
		"label": 734,
		"opcode": "EQUN",
		"flag": 0,
		"fixed_param": [],
		"raw_args": "76180000"
	},
	{
		"label": 742,
		"opcode": "EQUN",
		"flag": 0,
		"fixed_param": [],
		"raw_args": "77180000"
	},
	{
		"label": 750,
		"opcode": "EQUN",
		"flag": 0,
		"fixed_param": [],
		"raw_args": "78180000"
	},
	{
		"label": 758,
		"opcode": "EQUN",
		"flag": 0,
		"fixed_param": [],
		"raw_args": "79180000"
	},
	{
		"label": 766,
		"opcode": "EQUN",
		"flag": 0,
		"fixed_param": [],
		"raw_args": "7a180000"
	},
	{
		"label": 774,
		"opcode": "EQUN",
		"flag": 0,
		"fixed_param": [],
		"raw_args": "4b010000"
	},
	{
		"label": 782,
		"opcode": "EQUN",
		"flag": 0,
		"fixed_param": [],
		"raw_args": "4c010000"
	},
	{
		"label": 790,
		"opcode": "EQUN",
		"flag": 0,
		"fixed_param": [],
		"raw_args": "4d010000"
	},
	{
		"label": 798,
		"opcode": "EQUN",
		"flag": 0,
		"fixed_param": [],
		"raw_args": "4e010000"
	},
	{
		"label": 806,
		"opcode": "EQUN",
		"flag": 0,
		"fixed_param": [],
		"raw_args": "4f010000"
	},
	{
		"label": 814,
		"opcode": "EQUN",
		"flag": 0,
		"fixed_param": [],
		"raw_args": "50010000"
	},
	{
		"label": 822,
		"opcode": "EQUN",
		"flag": 0,
		"fixed_param": [],
		"raw_args": "51010000"
	},
	{
		"label": 830,
		"opcode": "EQUN",
		"flag": 0,
		"fixed_param": [],
		"raw_args": "52010000"
	},
	{
		"label": 838,
		"opcode": "EQUN",
		"flag": 0,
		"fixed_param": [],
		"raw_args": "53010000"
	},
	{
		"label": 846,
		"opcode": "EQUN",
		"flag": 0,
		"fixed_param": [],
		"raw_args": "54010000"
	},
	{
		"label": 854,
		"opcode": "IFN",
		"flag": 1,
		"fixed_param": [
			88
		],
		"condition": "(#6279==0)",
		"jump_pos": 936
	},
	{
		"label": 876,
		"opcode": "EQU",
		"flag": 1,
		"fixed_param": [
			89
		],
		"raw_args": "e21f233831363400"
	},
	{
		"label": 890,
		"opcode": "EQU",
		"flag": 1,
		"fixed_param": [
			90
		],
		"raw_args": "e31f233831363500"
	},
	{
		"label": 904,
		"opcode": "FARCALL",
		"flag": 1,
		"fixed_param": [
			91
		],
		"index": 4,
		"filename": "seen8540",
		"jump_pos": 8572,
		"end": null
	},
	{
		"label": 926,
		"opcode": "GOTO",
		"flag": 1,
		"fixed_param": [
			92
		],
		"jump_pos": 936
	},
	{
		"label": 936,
		"opcode": "BATTLE",
		"flag": 1,
		"fixed_param": [
			109
		],
		"battle_type": 1,
		"raw_args": "0100"
	},
	{
		"label": 944,
		"opcode": "WAIT",
		"flag": 1,
		"fixed_param": [
			112
		],
		"raw_args": "0c00"
	},
	{
		"label": 952,
		"opcode": "KOEP",
		"flag": 1,
		"fixed_param": [
			116
		],
		"raw_args": "0d0048110300"
	},
	{
		"label": 964,
		"opcode": "BATTLE",
		"flag": 1,
		"fixed_param": [
			119
		],
		"battle_type": 2,
		"raw_args": "0200"
	},
	{
		"label": 972,
		"opcode": "WAIT",
		"flag": 1,
		"fixed_param": [
			120
		],
		"raw_args": "1e00"
	},
	{
		"label": 980,
		"opcode": "BATTLE",
		"flag": 1,
		"fixed_param": [
			121
		],
		"battle_type": 6,
		"raw_args": "0600"
	},
	{
		"label": 988,
		"opcode": "EQU",
		"flag": 1,
		"fixed_param": [
			128
		],
		"raw_args": "f155233632323600"
	},
	{
		"label": 1002,
		"opcode": "EQU",
		"flag": 0,
		"fixed_param": [],
		"raw_args": "5218233632323700"
	},
	{
		"label": 1014,
		"opcode": "EQU",
		"flag": 0,
		"fixed_param": [],
		"raw_args": "531823323230303100"
	},
	{
		"label": 1028,
		"opcode": "BATTLE",
		"flag": 1,
		"fixed_param": [
			129
		],
		"battle_type": 100,
		"raw_args": "6400"
	},
	{
		"label": 1036,
		"opcode": "BATTLE",
		"flag": 1,
		"fixed_param": [
			131
		],
		"battle_type": 101,
		"var1": 954,
		"var2": null,
		"var3": null,
		"expr": null,
		"msg_jp": "「いけぇっ」",
		"msg_en": "❝Go!❞",
		"expr2": null,
		"msg_jp2": null,
		"msg_en2": null,
		"expr3": null,
		"msg_jp3": null,
		"msg_en3": null
	},
	{
		"label": 1072,
		"opcode": "BATTLE",
		"flag": 1,
		"fixed_param": [
			132
		],
		"battle_type": 201,
		"raw_args": "c900"
	},
	{
		"label": 1080,
		"opcode": "WAIT",
		"flag": 1,
		"fixed_param": [
			133
		],
		"raw_args": "2400"
	},
	{
		"label": 1088,
		"opcode": "BATTLE",
		"flag": 1,
		"fixed_param": [
			134
		],
		"battle_type": 102,
		"var1": null,
		"var2": null,
		"var3": null,
		"expr": null,
		"msg_jp": "鈴の攻撃！",
		"msg_en": "Rin attacks!",
		"expr2": null,
		"msg_jp2": null,
		"msg_en2": null,
		"expr3": null,
		"msg_jp3": null,
		"msg_en3": null
	},
	{
		"label": 1134,
		"opcode": "WAIT",
		"flag": 0,
		"fixed_param": [],
		"raw_args": "2400"
	},
	{
		"label": 1140,
		"opcode": "KOEP",
		"flag": 1,
		"fixed_param": [
			136
		],
		"raw_args": "0f006a0d0300"
	},
	{
		"label": 1152,
		"opcode": "BATTLE",
		"flag": 1,
		"fixed_param": [
			137
		],
		"battle_type": 102,
		"var1": null,
		"var2": null,
		"var3": null,
		"expr": null,
		"msg_jp": "鈴は猫たちを放った！",
		"msg_en": "Rin lets the cats loose!",
		"expr2": null,
		"msg_jp2": null,
		"msg_en2": null,
		"expr3": null,
		"msg_jp3": null,
		"msg_en3": null
	},
	{
		"label": 1232,
		"opcode": "WAIT",
		"flag": 0,
		"fixed_param": [],
		"raw_args": "3000"
	},
	{
		"label": 1238,
		"opcode": "EQUN",
		"flag": 1,
		"fixed_param": [
			138
		],
		"raw_args": "214e0000"
	},
	{
		"label": 1248,
		"opcode": "IFN",
		"flag": 0,
		"fixed_param": [],
		"condition": "(#20001<12)",
		"jump_pos": 3168
	},
	{
		"label": 1268,
		"opcode": "IFN",
		"flag": 1,
		"fixed_param": [
			140
		],
		"condition": "((#20001)==0)",
		"jump_pos": 1384
	},
	{
		"label": 1292,
		"opcode": "BATTLE",
		"flag": 0,
		"fixed_param": [],
		"battle_type": 102,
		"var1": null,
		"var2": null,
		"var3": null,
		"expr": null,
		"msg_jp": "にゃあ！　ヒトラーは飛びかかった！",
		"msg_en": "Meow! Hitler leaps!",
		"expr2": null,
		"msg_jp2": null,
		"msg_en2": null,
		"expr3": null,
		"msg_jp3": null,
		"msg_en3": null
	},
	{
		"label": 1374,
		"opcode": "GOTO",
		"flag": 1,
		"fixed_param": [
			141
		],
		"jump_pos": 2682
	},
	{
		"label": 1384,
		"opcode": "IFN",
		"flag": 1,
		"fixed_param": [
			141
		],
		"condition": "((#20001)==1)",
		"jump_pos": 1500
	},
	{
		"label": 1408,
		"opcode": "BATTLE",
		"flag": 0,
		"fixed_param": [],
		"battle_type": 102,
		"var1": null,
		"var2": null,
		"var3": null,
		"expr": null,
		"msg_jp": "にゃあ！　ファーブルは飛びかかった！",
		"msg_en": "Meow! Fabre leaps!",
		"expr2": null,
		"msg_jp2": null,
		"msg_en2": null,
		"expr3": null,
		"msg_jp3": null,
		"msg_en3": null
	},
	{
		"label": 1490,
		"opcode": "GOTO",
		"flag": 1,
		"fixed_param": [
			142
		],
		"jump_pos": 2682
	},
	{
		"label": 1500,
		"opcode": "IFN",
		"flag": 1,
		"fixed_param": [
			142
		],
		"condition": "((#20001)==2)",
		"jump_pos": 1618
	},
	{
		"label": 1524,
		"opcode": "BATTLE",
		"flag": 0,
		"fixed_param": [],
		"battle_type": 102,
		"var1": null,
		"var2": null,
		"var3": null,
		"expr": null,
		"msg_jp": "にゃあ！　オードリーは飛びかかった！",
		"msg_en": "Meow! Audrey leaps!",
		"expr2": null,
		"msg_jp2": null,
		"msg_en2": null,
		"expr3": null,
		"msg_jp3": null,
		"msg_en3": null
	},
	{
		"label": 1608,
		"opcode": "GOTO",
		"flag": 1,
		"fixed_param": [
			143
		],
		"jump_pos": 2682
	},
	{
		"label": 1618,
		"opcode": "IFN",
		"flag": 1,
		"fixed_param": [
			143
		],
		"condition": "((#20001)==3)",
		"jump_pos": 1734
	},
	{
		"label": 1642,
		"opcode": "BATTLE",
		"flag": 0,
		"fixed_param": [],
		"battle_type": 102,
		"var1": null,
		"var2": null,
		"var3": null,
		"expr": null,
		"msg_jp": "にゃあ！　コバーンは飛びかかった！",
		"msg_en": "Meow! Cobain leaps!",
		"expr2": null,
		"msg_jp2": null,
		"msg_en2": null,
		"expr3": null,
		"msg_jp3": null,
		"msg_en3": null
	},
	{
		"label": 1724,
		"opcode": "GOTO",
		"flag": 1,
		"fixed_param": [
			144
		],
		"jump_pos": 2682
	},
	{
		"label": 1734,
		"opcode": "IFN",
		"flag": 1,
		"fixed_param": [
			144
		],
		"condition": "((#20001)==4)",
		"jump_pos": 1848
	},
	{
		"label": 1758,
		"opcode": "BATTLE",
		"flag": 0,
		"fixed_param": [],
		"battle_type": 102,
		"var1": null,
		"var2": null,
		"var3": null,
		"expr": null,
		"msg_jp": "にゃあ！　テヅカは飛びかかった！",
		"msg_en": "Meow! Tezuka leaps!",
		"expr2": null,
		"msg_jp2": null,
		"msg_en2": null,
		"expr3": null,
		"msg_jp3": null,
		"msg_en3": null
	},
	{
		"label": 1838,
		"opcode": "GOTO",
		"flag": 1,
		"fixed_param": [
			145
		],
		"jump_pos": 2682
	},
	{
		"label": 1848,
		"opcode": "IFN",
		"flag": 1,
		"fixed_param": [
			145
		],
		"condition": "((#20001)==5)",
		"jump_pos": 1960
	},
	{
		"label": 1872,
		"opcode": "BATTLE",
		"flag": 0,
		"fixed_param": [],
		"battle_type": 102,
		"var1": null,
		"var2": null,
		"var3": null,
		"expr": null,
		"msg_jp": "にゃあ！　ゲイツは飛びかかった！",
		"msg_en": "Meow! Gates leaps!",
		"expr2": null,
		"msg_jp2": null,
		"msg_en2": null,
		"expr3": null,
		"msg_jp3": null,
		"msg_en3": null
	},
	{
		"label": 1950,
		"opcode": "GOTO",
		"flag": 1,
		"fixed_param": [
			146
		],
		"jump_pos": 2682
	},
	{
		"label": 1960,
		"opcode": "IFN",
		"flag": 1,
		"fixed_param": [
			146
		],
		"condition": "((#20001)==6)",
		"jump_pos": 2088
	},
	{
		"label": 1984,
		"opcode": "BATTLE",
		"flag": 0,
		"fixed_param": [],
		"battle_type": 102,
		"var1": null,
		"var2": null,
		"var3": null,
		"expr": null,
		"msg_jp": "にゃあ！　アインシュタインは飛びかかった！",
		"msg_en": "Meow! Einstein leaps!",
		"expr2": null,
		"msg_jp2": null,
		"msg_en2": null,
		"expr3": null,
		"msg_jp3": null,
		"msg_en3": null
	},
	{
		"label": 2078,
		"opcode": "GOTO",
		"flag": 1,
		"fixed_param": [
			147
		],
		"jump_pos": 2682
	},
	{
		"label": 2088,
		"opcode": "IFN",
		"flag": 1,
		"fixed_param": [
			147
		],
		"condition": "((#20001)==7)",
		"jump_pos": 2206
	},
	{
		"label": 2112,
		"opcode": "BATTLE",
		"flag": 0,
		"fixed_param": [],
		"battle_type": 102,
		"var1": null,
		"var2": null,
		"var3": null,
		"expr": null,
		"msg_jp": "にゃあ！　ヒョードルは飛びかかった！",
		"msg_en": "Meow! Fyodor leaps!",
		"expr2": null,
		"msg_jp2": null,
		"msg_en2": null,
		"expr3": null,
		"msg_jp3": null,
		"msg_en3": null
	},
	{
		"label": 2196,
		"opcode": "GOTO",
		"flag": 1,
		"fixed_param": [
			148
		],
		"jump_pos": 2682
	},
	{
		"label": 2206,
		"opcode": "IFN",
		"flag": 1,
		"fixed_param": [
			148
		],
		"condition": "((#20001)==8)",
		"jump_pos": 2334
	},
	{
		"label": 2230,
		"opcode": "BATTLE",
		"flag": 0,
		"fixed_param": [],
		"battle_type": 102,
		"var1": null,
		"var2": null,
		"var3": null,
		"expr": null,
		"msg_jp": "にゃあ！　アリストテレスは飛びかかった！",
		"msg_en": "Meow! Aristotle leaps!",
		"expr2": null,
		"msg_jp2": null,
		"msg_en2": null,
		"expr3": null,
		"msg_jp3": null,
		"msg_en3": null
	},
	{
		"label": 2324,
		"opcode": "GOTO",
		"flag": 1,
		"fixed_param": [
			149
		],
		"jump_pos": 2682
	},
	{
		"label": 2334,
		"opcode": "IFN",
		"flag": 1,
		"fixed_param": [
			149
		],
		"condition": "((#20001)==9)",
		"jump_pos": 2452
	},
	{
		"label": 2358,
		"opcode": "BATTLE",
		"flag": 0,
		"fixed_param": [],
		"battle_type": 102,
		"var1": null,
		"var2": null,
		"var3": null,
		"expr": null,
		"msg_jp": "にゃあ！　ホクサイは飛びかかった！",
		"msg_en": "Meow! Hokusai leaps!",
		"expr2": null,
		"msg_jp2": null,
		"msg_en2": null,
		"expr3": null,
		"msg_jp3": null,
		"msg_en3": null
	},
	{
		"label": 2442,
		"opcode": "GOTO",
		"flag": 1,
		"fixed_param": [
			150
		],
		"jump_pos": 2682
	},
	{
		"label": 2452,
		"opcode": "IFN",
		"flag": 1,
		"fixed_param": [
			150
		],
		"condition": "((#20001)==10)",
		"jump_pos": 2572
	},
	{
		"label": 2478,
		"opcode": "BATTLE",
		"flag": 0,
		"fixed_param": [],
		"battle_type": 102,
		"var1": null,
		"var2": null,
		"var3": null,
		"expr": null,
		"msg_jp": "にゃあ！　ジャッキーは飛びかかった！",
		"msg_en": "Meow! Jackie leaps!",
		"expr2": null,
		"msg_jp2": null,
		"msg_en2": null,
		"expr3": null,
		"msg_jp3": null,
		"msg_en3": null
	},
	{
		"label": 2562,
		"opcode": "GOTO",
		"flag": 1,
		"fixed_param": [
			151
		],
		"jump_pos": 2682
	},
	{
		"label": 2572,
		"opcode": "IFN",
		"flag": 1,
		"fixed_param": [
			151
		],
		"condition": "((#20001)==11)",
		"jump_pos": 2682
	},
	{
		"label": 2598,
		"opcode": "BATTLE",
		"flag": 0,
		"fixed_param": [],
		"battle_type": 102,
		"var1": null,
		"var2": null,
		"var3": null,
		"expr": null,
		"msg_jp": "にゃあ！　ユウサクは飛びかかった！",
		"msg_en": "Meow! Yuusaku leaps!",
		"expr2": null,
		"msg_jp2": null,
		"msg_en2": null,
		"expr3": null,
		"msg_jp3": null,
		"msg_en3": null
	},
	{
		"label": 2682,
		"opcode": "SE",
		"flag": 1,
		"fixed_param": [
			153
		],
		"raw_args": "ffb5120300"
	},
	{
		"label": 2694,
		"opcode": "FARCALL",
		"flag": 1,
		"fixed_param": [
			154
		],
		"index": 5,
		"filename": "seen8693",
		"jump_pos": 24934,
		"end": "233632323700"
	},
	{
		"label": 2722,
		"opcode": "BATTLE",
		"flag": 1,
		"fixed_param": [
			155
		],
		"battle_type": 221,
		"raw_args": "dd00"
	},
	{
		"label": 2730,
		"opcode": "SUB",
		"flag": 1,
		"fixed_param": [
			156
		],
		"raw_args": "04e02336323237003500"
	},
	{
		"label": 2746,
		"opcode": "IFN",
		"flag": 0,
		"fixed_param": [],
		"condition": "(#8188[#6227]<0)",
		"jump_pos": 2794
	},
	{
		"label": 2772,
		"opcode": "EQUN",
		"flag": 0,
		"fixed_param": [],
		"raw_args": "04e02336323237000000"
	},
	{
		"label": 2786,
		"opcode": "GOTO",
		"flag": 0,
		"fixed_param": [],
		"jump_pos": 2794
	},
	{
		"label": 2794,
		"opcode": "IFN",
		"flag": 1,
		"fixed_param": [
			157
		],
		"condition": "(#325==0)",
		"jump_pos": 2874
	},
	{
		"label": 2814,
		"opcode": "IFN",
		"flag": 0,
		"fixed_param": [],
		"condition": "(#6226==0)",
		"jump_pos": 2864
	},
	{
		"label": 2834,
		"opcode": "BATTLE",
		"flag": 0,
		"fixed_param": [],
		"battle_type": 300,
		"raw_args": "2c0123363231325b23363232365d003000"
	},
	{
		"label": 2856,
		"opcode": "GOTO",
		"flag": 0,
		"fixed_param": [],
		"jump_pos": 2864
	},
	{
		"label": 2864,
		"opcode": "GOTO",
		"flag": 1,
		"fixed_param": [
			157
		],
		"jump_pos": 2924
	},
	{
		"label": 2874,
		"opcode": "IFN",
		"flag": 1,
		"fixed_param": [
			157
		],
		"condition": "(#325==1)",
		"jump_pos": 2924
	},
	{
		"label": 2894,
		"opcode": "BATTLE",
		"flag": 0,
		"fixed_param": [],
		"battle_type": 300,
		"raw_args": "2c0123363231325b23363232365d003000"
	},
	{
		"label": 2916,
		"opcode": "GOTO",
		"flag": 0,
		"fixed_param": [],
		"jump_pos": 2924
	},
	{
		"label": 2924,
		"opcode": "BATTLE",
		"flag": 1,
		"fixed_param": [
			158
		],
		"battle_type": 102,
		"var1": null,
		"var2": null,
		"var3": null,
		"expr": null,
		"msg_jp": "真人に５のダメージ！",
		"msg_en": "Masato takes 5 damage!",
		"expr2": null,
		"msg_jp2": null,
		"msg_en2": null,
		"expr3": null,
		"msg_jp3": null,
		"msg_en3": null
	},
	{
		"label": 3000,
		"opcode": "WAIT",
		"flag": 1,
		"fixed_param": [
			159
		],
		"raw_args": "0900"
	},
	{
		"label": 3008,
		"opcode": "IFN",
		"flag": 1,
		"fixed_param": [
			160
		],
		"condition": "((#325==0)&&(#6226==1))",
		"jump_pos": 3058
	},
	{
		"label": 3042,
		"opcode": "BATTLE",
		"flag": 0,
		"fixed_param": [],
		"battle_type": 302,
		"raw_args": "2e013000"
	},
	{
		"label": 3050,
		"opcode": "GOTO",
		"flag": 0,
		"fixed_param": [],
		"jump_pos": 3068
	},
	{
		"label": 3058,
		"opcode": "BATTLE",
		"flag": 1,
		"fixed_param": [
			160
		],
		"battle_type": 301,
		"raw_args": "2d013000"
	},
	{
		"label": 3068,
		"opcode": "FARCALL",
		"flag": 1,
		"fixed_param": [
			161
		],
		"index": 6,
		"filename": "seen8600",
		"jump_pos": 6436,
		"end": null
	},
	{
		"label": 3090,
		"opcode": "BATTLE",
		"flag": 1,
		"fixed_param": [
			162
		],
		"battle_type": 110,
		"raw_args": "6e00"
	},
	{
		"label": 3098,
		"opcode": "IFN",
		"flag": 1,
		"fixed_param": [
			163
		],
		"condition": "(#20001<(12-1))",
		"jump_pos": 3138
	},
	{
		"label": 3124,
		"opcode": "WAIT",
		"flag": 0,
		"fixed_param": [],
		"raw_args": "0900"
	},
	{
		"label": 3130,
		"opcode": "GOTO",
		"flag": 0,
		"fixed_param": [],
		"jump_pos": 3138
	},
	{
		"label": 3138,
		"opcode": "ADD",
		"flag": 1,
		"fixed_param": [
			164
		],
		"raw_args": "214e3100"
	},
	{
		"label": 3148,
		"opcode": "IFY",
		"flag": 0,
		"fixed_param": [],
		"condition": "(#20001<12)",
		"jump_pos": 1268
	},
	{
		"label": 3168,
		"opcode": "BATTLE",
		"flag": 1,
		"fixed_param": [
			165
		],
		"battle_type": 111,
		"raw_args": "6f00"
	},
	{
		"label": 3176,
		"opcode": "EQU",
		"flag": 1,
		"fixed_param": [
			166
		],
		"raw_args": "f155233632323600"
	},
	{
		"label": 3190,
		"opcode": "EQU",
		"flag": 0,
		"fixed_param": [],
		"raw_args": "5218233632323700"
	},
	{
		"label": 3202,
		"opcode": "EQU",
		"flag": 0,
		"fixed_param": [],
		"raw_args": "531823323230303100"
	},
	{
		"label": 3216,
		"opcode": "BATTLE",
		"flag": 1,
		"fixed_param": [
			169
		],
		"battle_type": 100,
		"raw_args": "6400"
	},
	{
		"label": 3224,
		"opcode": "BATTLE",
		"flag": 1,
		"fixed_param": [
			171
		],
		"battle_type": 101,
		"var1": 955,
		"var2": null,
		"var3": null,
		"expr": null,
		"msg_jp": "「やるじゃねぇか…今度はこっちからいくぜ」",
		"msg_en": "❝Not bad... it's my turn now.❞",
		"expr2": null,
		"msg_jp2": null,
		"msg_en2": null,
		"expr3": null,
		"msg_jp3": null,
		"msg_en3": null
	},
	{
		"label": 3340,
		"opcode": "BATTLE",
		"flag": 1,
		"fixed_param": [
			172
		],
		"battle_type": 200,
		"raw_args": "c800"
	},
	{
		"label": 3348,
		"opcode": "WAIT",
		"flag": 1,
		"fixed_param": [
			173
		],
		"raw_args": "ae00"
	},
	{
		"label": 3356,
		"opcode": "BATTLE",
		"flag": 1,
		"fixed_param": [
			174
		],
		"battle_type": 102,
		"var1": null,
		"var2": null,
		"var3": null,
		"expr": null,
		"msg_jp": "真人の攻撃！",
		"msg_en": "Masato attacks!",
		"expr2": null,
		"msg_jp2": null,
		"msg_en2": null,
		"expr3": null,
		"msg_jp3": null,
		"msg_en3": null
	},
	{
		"label": 3410,
		"opcode": "WAIT",
		"flag": 0,
		"fixed_param": [],
		"raw_args": "2400"
	},
	{
		"label": 3416,
		"opcode": "KOEP",
		"flag": 1,
		"fixed_param": [
			176
		],
		"raw_args": "0e0050100300"
	},
	{
		"label": 3428,
		"opcode": "BATTLE",
		"flag": 1,
		"fixed_param": [
			177
		],
		"battle_type": 102,
		"var1": null,
		"var2": null,
		"var3": null,
		"expr": null,
		"msg_jp": "真人は爪切りで鈴の爪を切った！",
		"msg_en": "Masato trims Rin's nail with the nail clippers!",
		"expr2": null,
		"msg_jp2": null,
		"msg_en2": null,
		"expr3": null,
		"msg_jp3": null,
		"msg_en3": null
	},
	{
		"label": 3564,
		"opcode": "WAIT",
		"flag": 0,
		"fixed_param": [],
		"raw_args": "3000"
	},
	{
		"label": 3570,
		"opcode": "EQUN",
		"flag": 1,
		"fixed_param": [
			178
		],
		"raw_args": "214e0000"
	},
	{
		"label": 3580,
		"opcode": "IFN",
		"flag": 0,
		"fixed_param": [],
		"condition": "(#20001<1)",
		"jump_pos": 4010
	},
	{
		"label": 3600,
		"opcode": "SE",
		"flag": 1,
		"fixed_param": [
			179
		],
		"raw_args": "ffb5120300"
	},
	{
		"label": 3612,
		"opcode": "FARCALL",
		"flag": 1,
		"fixed_param": [
			180
		],
		"index": 7,
		"filename": "seen8693",
		"jump_pos": 24934,
		"end": "233632323700"
	},
	{
		"label": 3640,
		"opcode": "BATTLE",
		"flag": 1,
		"fixed_param": [
			182
		],
		"battle_type": 223,
		"raw_args": "df00"
	},
	{
		"label": 3648,
		"opcode": "SUB",
		"flag": 1,
		"fixed_param": [
			183
		],
		"raw_args": "04e02336323237003000"
	},
	{
		"label": 3664,
		"opcode": "IFN",
		"flag": 0,
		"fixed_param": [],
		"condition": "(#8188[#6227]<0)",
		"jump_pos": 3712
	},
	{
		"label": 3690,
		"opcode": "EQUN",
		"flag": 0,
		"fixed_param": [],
		"raw_args": "04e02336323237000000"
	},
	{
		"label": 3704,
		"opcode": "GOTO",
		"flag": 0,
		"fixed_param": [],
		"jump_pos": 3712
	},
	{
		"label": 3712,
		"opcode": "IFN",
		"flag": 1,
		"fixed_param": [
			184
		],
		"condition": "(#325==0)",
		"jump_pos": 3792
	},
	{
		"label": 3732,
		"opcode": "IFN",
		"flag": 0,
		"fixed_param": [],
		"condition": "(#6226==0)",
		"jump_pos": 3782
	},
	{
		"label": 3752,
		"opcode": "BATTLE",
		"flag": 0,
		"fixed_param": [],
		"battle_type": 300,
		"raw_args": "2c0123363231325b23363232365d003000"
	},
	{
		"label": 3774,
		"opcode": "GOTO",
		"flag": 0,
		"fixed_param": [],
		"jump_pos": 3782
	},
	{
		"label": 3782,
		"opcode": "GOTO",
		"flag": 1,
		"fixed_param": [
			184
		],
		"jump_pos": 3842
	},
	{
		"label": 3792,
		"opcode": "IFN",
		"flag": 1,
		"fixed_param": [
			184
		],
		"condition": "(#325==1)",
		"jump_pos": 3842
	},
	{
		"label": 3812,
		"opcode": "BATTLE",
		"flag": 0,
		"fixed_param": [],
		"battle_type": 300,
		"raw_args": "2c0123363231325b23363232365d003000"
	},
	{
		"label": 3834,
		"opcode": "GOTO",
		"flag": 0,
		"fixed_param": [],
		"jump_pos": 3842
	},
	{
		"label": 3842,
		"opcode": "WAIT",
		"flag": 1,
		"fixed_param": [
			185
		],
		"raw_args": "0900"
	},
	{
		"label": 3850,
		"opcode": "IFN",
		"flag": 1,
		"fixed_param": [
			186
		],
		"condition": "((#325==0)&&(#6226==1))",
		"jump_pos": 3900
	},
	{
		"label": 3884,
		"opcode": "BATTLE",
		"flag": 0,
		"fixed_param": [],
		"battle_type": 302,
		"raw_args": "2e013000"
	},
	{
		"label": 3892,
		"opcode": "GOTO",
		"flag": 0,
		"fixed_param": [],
		"jump_pos": 3910
	},
	{
		"label": 3900,
		"opcode": "BATTLE",
		"flag": 1,
		"fixed_param": [
			186
		],
		"battle_type": 301,
		"raw_args": "2d013000"
	},
	{
		"label": 3910,
		"opcode": "FARCALL",
		"flag": 1,
		"fixed_param": [
			187
		],
		"index": 8,
		"filename": "seen8600",
		"jump_pos": 6436,
		"end": null
	},
	{
		"label": 3932,
		"opcode": "BATTLE",
		"flag": 1,
		"fixed_param": [
			188
		],
		"battle_type": 110,
		"raw_args": "6e00"
	},
	{
		"label": 3940,
		"opcode": "IFN",
		"flag": 1,
		"fixed_param": [
			189
		],
		"condition": "(#20001<(1-1))",
		"jump_pos": 3980
	},
	{
		"label": 3966,
		"opcode": "WAIT",
		"flag": 0,
		"fixed_param": [],
		"raw_args": "0900"
	},
	{
		"label": 3972,
		"opcode": "GOTO",
		"flag": 0,
		"fixed_param": [],
		"jump_pos": 3980
	},
	{
		"label": 3980,
		"opcode": "ADD",
		"flag": 1,
		"fixed_param": [
			190
		],
		"raw_args": "214e3100"
	},
	{
		"label": 3990,
		"opcode": "IFY",
		"flag": 0,
		"fixed_param": [],
		"condition": "(#20001<1)",
		"jump_pos": 3600
	},
	{
		"label": 4010,
		"opcode": "WAIT",
		"flag": 1,
		"fixed_param": [
			191
		],
		"raw_args": "0900"
	},
	{
		"label": 4018,
		"opcode": "BATTLE",
		"flag": 1,
		"fixed_param": [
			192
		],
		"battle_type": 102,
		"var1": null,
		"var2": null,
		"var3": null,
		"expr": null,
		"msg_jp": "鈴の指が深爪になった！",
		"msg_en": "Rin's nail was fully trimmed.",
		"expr2": null,
		"msg_jp2": null,
		"msg_en2": null,
		"expr3": null,
		"msg_jp3": null,
		"msg_en3": null
	},
	{
		"label": 4110,
		"opcode": "BATTLE",
		"flag": 1,
		"fixed_param": [
			193
		],
		"battle_type": 110,
		"raw_args": "6e00"
	},
	{
		"label": 4118,
		"opcode": "WAIT",
		"flag": 1,
		"fixed_param": [
			194
		],
		"raw_args": "1800"
	},
	{
		"label": 4126,
		"opcode": "BATTLE",
		"flag": 1,
		"fixed_param": [
			196
		],
		"battle_type": 101,
		"var1": 956,
		"var2": null,
		"var3": null,
		"expr": null,
		"msg_jp": "「へっ、これでプルタブは開けられまい…」",
		"msg_en": "❝Heh, now you won't even be able to pull the tab off a can...❞",
		"expr2": null,
		"msg_jp2": null,
		"msg_en2": null,
		"expr3": null,
		"msg_jp3": null,
		"msg_en3": null
	},
	{
		"label": 4304,
		"opcode": "BATTLE",
		"flag": 1,
		"fixed_param": [
			197
		],
		"battle_type": 111,
		"raw_args": "6f00"
	},
	{
		"label": 4312,
		"opcode": "EQU",
		"flag": 1,
		"fixed_param": [
			198
		],
		"raw_args": "f155233632323600"
	},
	{
		"label": 4326,
		"opcode": "EQU",
		"flag": 0,
		"fixed_param": [],
		"raw_args": "5218233632323700"
	},
	{
		"label": 4338,
		"opcode": "EQU",
		"flag": 0,
		"fixed_param": [],
		"raw_args": "531823323230303100"
	},
	{
		"label": 4352,
		"opcode": "BATTLE",
		"flag": 1,
		"fixed_param": [
			201
		],
		"battle_type": 100,
		"raw_args": "6400"
	},
	{
		"label": 4360,
		"opcode": "BATTLE",
		"flag": 1,
		"fixed_param": [
			203
		],
		"battle_type": 101,
		"var1": 12849,
		"var2": null,
		"var3": null,
		"expr": null,
		"msg_jp": "「あとでツナ缶あげるから、おまえらがんばれ」",
		"msg_en": "❝I'll open some canned tuna, so work hard!❞",
		"expr2": null,
		"msg_jp2": null,
		"msg_en2": null,
		"expr3": null,
		"msg_jp3": null,
		"msg_en3": null
	},
	{
		"label": 4504,
		"opcode": "BATTLE",
		"flag": 1,
		"fixed_param": [
			204
		],
		"battle_type": 201,
		"raw_args": "c900"
	},
	{
		"label": 4512,
		"opcode": "WAIT",
		"flag": 1,
		"fixed_param": [
			205
		],
		"raw_args": "9600"
	},
	{
		"label": 4520,
		"opcode": "BATTLE",
		"flag": 1,
		"fixed_param": [
			206
		],
		"battle_type": 102,
		"var1": null,
		"var2": null,
		"var3": null,
		"expr": null,
		"msg_jp": "うにゃあー!!",
		"msg_en": "Unyaa!!",
		"expr2": null,
		"msg_jp2": null,
		"msg_en2": null,
		"expr3": null,
		"msg_jp3": null,
		"msg_en3": null
	},
	{
		"label": 4560,
		"opcode": "BATTLE",
		"flag": 1,
		"fixed_param": [
			207
		],
		"battle_type": 102,
		"var1": null,
		"var2": null,
		"var3": null,
		"expr": null,
		"msg_jp": "猫たちの士気が上がった！",
		"msg_en": "The cats' morale went up!",
		"expr2": null,
		"msg_jp2": null,
		"msg_en2": null,
		"expr3": null,
		"msg_jp3": null,
		"msg_en3": null
	},
	{
		"label": 4646,
		"opcode": "BATTLE",
		"flag": 1,
		"fixed_param": [
			208
		],
		"battle_type": 111,
		"raw_args": "6f00"
	},
	{
		"label": 4654,
		"opcode": "BATTLE",
		"flag": 1,
		"fixed_param": [
			211
		],
		"battle_type": 100,
		"raw_args": "6400"
	},
	{
		"label": 4662,
		"opcode": "BATTLE",
		"flag": 1,
		"fixed_param": [
			213
		],
		"battle_type": 101,
		"var1": 957,
		"var2": null,
		"var3": null,
		"expr": null,
		"msg_jp": "「いけぇっ」",
		"msg_en": "❝Go!❞",
		"expr2": null,
		"msg_jp2": null,
		"msg_en2": null,
		"expr3": null,
		"msg_jp3": null,
		"msg_en3": null
	},
	{
		"label": 4698,
		"opcode": "WAIT",
		"flag": 1,
		"fixed_param": [
			214
		],
		"raw_args": "4200"
	},
	{
		"label": 4706,
		"opcode": "BATTLE",
		"flag": 1,
		"fixed_param": [
			215
		],
		"battle_type": 102,
		"var1": null,
		"var2": null,
		"var3": null,
		"expr": null,
		"msg_jp": "鈴の攻撃！",
		"msg_en": "Rin attacks!",
		"expr2": null,
		"msg_jp2": null,
		"msg_en2": null,
		"expr3": null,
		"msg_jp3": null,
		"msg_en3": null
	},
	{
		"label": 4752,
		"opcode": "WAIT",
		"flag": 0,
		"fixed_param": [],
		"raw_args": "2400"
	},
	{
		"label": 4758,
		"opcode": "KOEP",
		"flag": 1,
		"fixed_param": [
			217
		],
		"raw_args": "0f006c0d0300"
	},
	{
		"label": 4770,
		"opcode": "BATTLE",
		"flag": 1,
		"fixed_param": [
			218
		],
		"battle_type": 102,
		"var1": null,
		"var2": null,
		"var3": null,
		"expr": null,
		"msg_jp": "鈴は猫たちを放った！",
		"msg_en": "Rin lets the cats loose!",
		"expr2": null,
		"msg_jp2": null,
		"msg_en2": null,
		"expr3": null,
		"msg_jp3": null,
		"msg_en3": null
	},
	{
		"label": 4850,
		"opcode": "WAIT",
		"flag": 0,
		"fixed_param": [],
		"raw_args": "3000"
	},
	{
		"label": 4856,
		"opcode": "EQUN",
		"flag": 1,
		"fixed_param": [
			219
		],
		"raw_args": "214e0000"
	},
	{
		"label": 4866,
		"opcode": "IFN",
		"flag": 0,
		"fixed_param": [],
		"condition": "(#20001<12)",
		"jump_pos": 6884
	},
	{
		"label": 4886,
		"opcode": "IFN",
		"flag": 1,
		"fixed_param": [
			221
		],
		"condition": "((#20001)==0)",
		"jump_pos": 5002
	},
	{
		"label": 4910,
		"opcode": "BATTLE",
		"flag": 0,
		"fixed_param": [],
		"battle_type": 102,
		"var1": null,
		"var2": null,
		"var3": null,
		"expr": null,
		"msg_jp": "にゃあ！　ヒトラーは飛びかかった！",
		"msg_en": "Meow! Hitler leaps!",
		"expr2": null,
		"msg_jp2": null,
		"msg_en2": null,
		"expr3": null,
		"msg_jp3": null,
		"msg_en3": null
	},
	{
		"label": 4992,
		"opcode": "GOTO",
		"flag": 1,
		"fixed_param": [
			222
		],
		"jump_pos": 6300
	},
	{
		"label": 5002,
		"opcode": "IFN",
		"flag": 1,
		"fixed_param": [
			222
		],
		"condition": "((#20001)==1)",
		"jump_pos": 5118
	},
	{
		"label": 5026,
		"opcode": "BATTLE",
		"flag": 0,
		"fixed_param": [],
		"battle_type": 102,
		"var1": null,
		"var2": null,
		"var3": null,
		"expr": null,
		"msg_jp": "にゃあ！　ファーブルは飛びかかった！",
		"msg_en": "Meow! Fabre leaps!",
		"expr2": null,
		"msg_jp2": null,
		"msg_en2": null,
		"expr3": null,
		"msg_jp3": null,
		"msg_en3": null
	},
	{
		"label": 5108,
		"opcode": "GOTO",
		"flag": 1,
		"fixed_param": [
			223
		],
		"jump_pos": 6300
	},
	{
		"label": 5118,
		"opcode": "IFN",
		"flag": 1,
		"fixed_param": [
			223
		],
		"condition": "((#20001)==2)",
		"jump_pos": 5236
	},
	{
		"label": 5142,
		"opcode": "BATTLE",
		"flag": 0,
		"fixed_param": [],
		"battle_type": 102,
		"var1": null,
		"var2": null,
		"var3": null,
		"expr": null,
		"msg_jp": "にゃあ！　オードリーは飛びかかった！",
		"msg_en": "Meow! Audrey leaps!",
		"expr2": null,
		"msg_jp2": null,
		"msg_en2": null,
		"expr3": null,
		"msg_jp3": null,
		"msg_en3": null
	},
	{
		"label": 5226,
		"opcode": "GOTO",
		"flag": 1,
		"fixed_param": [
			224
		],
		"jump_pos": 6300
	},
	{
		"label": 5236,
		"opcode": "IFN",
		"flag": 1,
		"fixed_param": [
			224
		],
		"condition": "((#20001)==3)",
		"jump_pos": 5352
	},
	{
		"label": 5260,
		"opcode": "BATTLE",
		"flag": 0,
		"fixed_param": [],
		"battle_type": 102,
		"var1": null,
		"var2": null,
		"var3": null,
		"expr": null,
		"msg_jp": "にゃあ！　コバーンは飛びかかった！",
		"msg_en": "Meow! Cobain leaps!",
		"expr2": null,
		"msg_jp2": null,
		"msg_en2": null,
		"expr3": null,
		"msg_jp3": null,
		"msg_en3": null
	},
	{
		"label": 5342,
		"opcode": "GOTO",
		"flag": 1,
		"fixed_param": [
			225
		],
		"jump_pos": 6300
	},
	{
		"label": 5352,
		"opcode": "IFN",
		"flag": 1,
		"fixed_param": [
			225
		],
		"condition": "((#20001)==4)",
		"jump_pos": 5466
	},
	{
		"label": 5376,
		"opcode": "BATTLE",
		"flag": 0,
		"fixed_param": [],
		"battle_type": 102,
		"var1": null,
		"var2": null,
		"var3": null,
		"expr": null,
		"msg_jp": "にゃあ！　テヅカは飛びかかった！",
		"msg_en": "Meow! Tezuka leaps!",
		"expr2": null,
		"msg_jp2": null,
		"msg_en2": null,
		"expr3": null,
		"msg_jp3": null,
		"msg_en3": null
	},
	{
		"label": 5456,
		"opcode": "GOTO",
		"flag": 1,
		"fixed_param": [
			226
		],
		"jump_pos": 6300
	},
	{
		"label": 5466,
		"opcode": "IFN",
		"flag": 1,
		"fixed_param": [
			226
		],
		"condition": "((#20001)==5)",
		"jump_pos": 5578
	},
	{
		"label": 5490,
		"opcode": "BATTLE",
		"flag": 0,
		"fixed_param": [],
		"battle_type": 102,
		"var1": null,
		"var2": null,
		"var3": null,
		"expr": null,
		"msg_jp": "にゃあ！　ゲイツは飛びかかった！",
		"msg_en": "Meow! Gates leaps!",
		"expr2": null,
		"msg_jp2": null,
		"msg_en2": null,
		"expr3": null,
		"msg_jp3": null,
		"msg_en3": null
	},
	{
		"label": 5568,
		"opcode": "GOTO",
		"flag": 1,
		"fixed_param": [
			227
		],
		"jump_pos": 6300
	},
	{
		"label": 5578,
		"opcode": "IFN",
		"flag": 1,
		"fixed_param": [
			227
		],
		"condition": "((#20001)==6)",
		"jump_pos": 5706
	},
	{
		"label": 5602,
		"opcode": "BATTLE",
		"flag": 0,
		"fixed_param": [],
		"battle_type": 102,
		"var1": null,
		"var2": null,
		"var3": null,
		"expr": null,
		"msg_jp": "にゃあ！　アインシュタインは飛びかかった！",
		"msg_en": "Meow! Einstein leaps!",
		"expr2": null,
		"msg_jp2": null,
		"msg_en2": null,
		"expr3": null,
		"msg_jp3": null,
		"msg_en3": null
	},
	{
		"label": 5696,
		"opcode": "GOTO",
		"flag": 1,
		"fixed_param": [
			228
		],
		"jump_pos": 6300
	},
	{
		"label": 5706,
		"opcode": "IFN",
		"flag": 1,
		"fixed_param": [
			228
		],
		"condition": "((#20001)==7)",
		"jump_pos": 5824
	},
	{
		"label": 5730,
		"opcode": "BATTLE",
		"flag": 0,
		"fixed_param": [],
		"battle_type": 102,
		"var1": null,
		"var2": null,
		"var3": null,
		"expr": null,
		"msg_jp": "にゃあ！　ヒョードルは飛びかかった！",
		"msg_en": "Meow! Fyodor leaps!",
		"expr2": null,
		"msg_jp2": null,
		"msg_en2": null,
		"expr3": null,
		"msg_jp3": null,
		"msg_en3": null
	},
	{
		"label": 5814,
		"opcode": "GOTO",
		"flag": 1,
		"fixed_param": [
			229
		],
		"jump_pos": 6300
	},
	{
		"label": 5824,
		"opcode": "IFN",
		"flag": 1,
		"fixed_param": [
			229
		],
		"condition": "((#20001)==8)",
		"jump_pos": 5952
	},
	{
		"label": 5848,
		"opcode": "BATTLE",
		"flag": 0,
		"fixed_param": [],
		"battle_type": 102,
		"var1": null,
		"var2": null,
		"var3": null,
		"expr": null,
		"msg_jp": "にゃあ！　アリストテレスは飛びかかった！",
		"msg_en": "Meow! Aristotle leaps!",
		"expr2": null,
		"msg_jp2": null,
		"msg_en2": null,
		"expr3": null,
		"msg_jp3": null,
		"msg_en3": null
	},
	{
		"label": 5942,
		"opcode": "GOTO",
		"flag": 1,
		"fixed_param": [
			230
		],
		"jump_pos": 6300
	},
	{
		"label": 5952,
		"opcode": "IFN",
		"flag": 1,
		"fixed_param": [
			230
		],
		"condition": "((#20001)==9)",
		"jump_pos": 6070
	},
	{
		"label": 5976,
		"opcode": "BATTLE",
		"flag": 0,
		"fixed_param": [],
		"battle_type": 102,
		"var1": null,
		"var2": null,
		"var3": null,
		"expr": null,
		"msg_jp": "にゃあ！　ホクサイは飛びかかった！",
		"msg_en": "Meow! Hokusai leaps!",
		"expr2": null,
		"msg_jp2": null,
		"msg_en2": null,
		"expr3": null,
		"msg_jp3": null,
		"msg_en3": null
	},
	{
		"label": 6060,
		"opcode": "GOTO",
		"flag": 1,
		"fixed_param": [
			231
		],
		"jump_pos": 6300
	},
	{
		"label": 6070,
		"opcode": "IFN",
		"flag": 1,
		"fixed_param": [
			231
		],
		"condition": "((#20001)==10)",
		"jump_pos": 6190
	},
	{
		"label": 6096,
		"opcode": "BATTLE",
		"flag": 0,
		"fixed_param": [],
		"battle_type": 102,
		"var1": null,
		"var2": null,
		"var3": null,
		"expr": null,
		"msg_jp": "にゃあ！　ジャッキーは飛びかかった！",
		"msg_en": "Meow! Jackie leaps!",
		"expr2": null,
		"msg_jp2": null,
		"msg_en2": null,
		"expr3": null,
		"msg_jp3": null,
		"msg_en3": null
	},
	{
		"label": 6180,
		"opcode": "GOTO",
		"flag": 1,
		"fixed_param": [
			232
		],
		"jump_pos": 6300
	},
	{
		"label": 6190,
		"opcode": "IFN",
		"flag": 1,
		"fixed_param": [
			232
		],
		"condition": "((#20001)==11)",
		"jump_pos": 6300
	},
	{
		"label": 6216,
		"opcode": "BATTLE",
		"flag": 0,
		"fixed_param": [],
		"battle_type": 102,
		"var1": null,
		"var2": null,
		"var3": null,
		"expr": null,
		"msg_jp": "にゃあ！　ユウサクは飛びかかった！",
		"msg_en": "Meow! Yuusaku leaps!",
		"expr2": null,
		"msg_jp2": null,
		"msg_en2": null,
		"expr3": null,
		"msg_jp3": null,
		"msg_en3": null
	},
	{
		"label": 6300,
		"opcode": "SE",
		"flag": 1,
		"fixed_param": [
			234
		],
		"raw_args": "ffb6120300"
	},
	{
		"label": 6312,
		"opcode": "FARCALL",
		"flag": 1,
		"fixed_param": [
			235
		],
		"index": 9,
		"filename": "seen8693",
		"jump_pos": 28900,
		"end": "233632323700"
	},
	{
		"label": 6340,
		"opcode": "EQU",
		"flag": 1,
		"fixed_param": [
			236
		],
		"raw_args": "224e23383139302a31302f31303000"
	},
	{
		"label": 6362,
		"opcode": "RANDOM",
		"flag": 1,
		"fixed_param": [
			237
		],
		"var1": 20003,
		"rnd_from": "0",
		"rnd_to": "2"
	},
	{
		"label": 6374,
		"opcode": "EQU",
		"flag": 1,
		"fixed_param": [
			238
		],
		"raw_args": "244e2332303030322b23323030303300"
	},
	{
		"label": 6396,
		"opcode": "BATTLE",
		"flag": 1,
		"fixed_param": [
			239
		],
		"battle_type": 221,
		"raw_args": "dd00"
	},
	{
		"label": 6404,
		"opcode": "SUB",
		"flag": 1,
		"fixed_param": [
			240
		],
		"raw_args": "04e023363232370023323030303400"
	},
	{
		"label": 6426,
		"opcode": "IFN",
		"flag": 0,
		"fixed_param": [],
		"condition": "(#8188[#6227]<0)",
		"jump_pos": 6474
	},
	{
		"label": 6452,
		"opcode": "EQUN",
		"flag": 0,
		"fixed_param": [],
		"raw_args": "04e02336323237000000"
	},
	{
		"label": 6466,
		"opcode": "GOTO",
		"flag": 0,
		"fixed_param": [],
		"jump_pos": 6474
	},
	{
		"label": 6474,
		"opcode": "IFN",
		"flag": 1,
		"fixed_param": [
			241
		],
		"condition": "(#325==0)",
		"jump_pos": 6554
	},
	{
		"label": 6494,
		"opcode": "IFN",
		"flag": 0,
		"fixed_param": [],
		"condition": "(#6226==0)",
		"jump_pos": 6544
	},
	{
		"label": 6514,
		"opcode": "BATTLE",
		"flag": 0,
		"fixed_param": [],
		"battle_type": 300,
		"raw_args": "2c0123363231325b23363232365d003100"
	},
	{
		"label": 6536,
		"opcode": "GOTO",
		"flag": 0,
		"fixed_param": [],
		"jump_pos": 6544
	},
	{
		"label": 6544,
		"opcode": "GOTO",
		"flag": 1,
		"fixed_param": [
			241
		],
		"jump_pos": 6604
	},
	{
		"label": 6554,
		"opcode": "IFN",
		"flag": 1,
		"fixed_param": [
			241
		],
		"condition": "(#325==1)",
		"jump_pos": 6604
	},
	{
		"label": 6574,
		"opcode": "BATTLE",
		"flag": 0,
		"fixed_param": [],
		"battle_type": 300,
		"raw_args": "2c0123363231325b23363232365d003100"
	},
	{
		"label": 6596,
		"opcode": "GOTO",
		"flag": 0,
		"fixed_param": [],
		"jump_pos": 6604
	},
	{
		"label": 6604,
		"opcode": "BATTLE",
		"flag": 1,
		"fixed_param": [
			242
		],
		"battle_type": 102,
		"var1": null,
		"var2": null,
		"var3": null,
		"expr": null,
		"msg_jp": "真人に$V(#20004)のダメージ！",
		"msg_en": "Masato takes $v(#20004) damage!",
		"expr2": null,
		"msg_jp2": null,
		"msg_en2": null,
		"expr3": null,
		"msg_jp3": null,
		"msg_en3": null
	},
	{
		"label": 6716,
		"opcode": "WAIT",
		"flag": 1,
		"fixed_param": [
			243
		],
		"raw_args": "0900"
	},
	{
		"label": 6724,
		"opcode": "IFN",
		"flag": 1,
		"fixed_param": [
			244
		],
		"condition": "((#325==0)&&(#6226==1))",
		"jump_pos": 6774
	},
	{
		"label": 6758,
		"opcode": "BATTLE",
		"flag": 0,
		"fixed_param": [],
		"battle_type": 302,
		"raw_args": "2e013100"
	},
	{
		"label": 6766,
		"opcode": "GOTO",
		"flag": 0,
		"fixed_param": [],
		"jump_pos": 6784
	},
	{
		"label": 6774,
		"opcode": "BATTLE",
		"flag": 1,
		"fixed_param": [
			244
		],
		"battle_type": 301,
		"raw_args": "2d013100"
	},
	{
		"label": 6784,
		"opcode": "FARCALL",
		"flag": 1,
		"fixed_param": [
			245
		],
		"index": 10,
		"filename": "seen8600",
		"jump_pos": 6436,
		"end": null
	},
	{
		"label": 6806,
		"opcode": "BATTLE",
		"flag": 1,
		"fixed_param": [
			246
		],
		"battle_type": 110,
		"raw_args": "6e00"
	},
	{
		"label": 6814,
		"opcode": "IFN",
		"flag": 1,
		"fixed_param": [
			247
		],
		"condition": "(#20001<(12-1))",
		"jump_pos": 6854
	},
	{
		"label": 6840,
		"opcode": "WAIT",
		"flag": 0,
		"fixed_param": [],
		"raw_args": "0900"
	},
	{
		"label": 6846,
		"opcode": "GOTO",
		"flag": 0,
		"fixed_param": [],
		"jump_pos": 6854
	},
	{
		"label": 6854,
		"opcode": "ADD",
		"flag": 1,
		"fixed_param": [
			248
		],
		"raw_args": "214e3100"
	},
	{
		"label": 6864,
		"opcode": "IFY",
		"flag": 0,
		"fixed_param": [],
		"condition": "(#20001<12)",
		"jump_pos": 4886
	},
	{
		"label": 6884,
		"opcode": "WAIT",
		"flag": 1,
		"fixed_param": [
			249
		],
		"raw_args": "0900"
	},
	{
		"label": 6892,
		"opcode": "WAIT",
		"flag": 1,
		"fixed_param": [
			258
		],
		"raw_args": "1e00"
	},
	{
		"label": 6900,
		"opcode": "SE",
		"flag": 1,
		"fixed_param": [
			261
		],
		"raw_args": "ffc0120300"
	},
	{
		"label": 6912,
		"opcode": "BATTLE",
		"flag": 1,
		"fixed_param": [
			266
		],
		"battle_type": 101,
		"var1": 958,
		"var2": 0,
		"var3": 0,
		"expr": "#6168",
		"msg_jp": "は倒れた！",
		"msg_en": " falls!",
		"expr2": null,
		"msg_jp2": null,
		"msg_en2": null,
		"expr3": null,
		"msg_jp3": null,
		"msg_en3": null
	},
	{
		"label": 6960,
		"opcode": "BATTLE",
		"flag": 1,
		"fixed_param": [
			269
		],
		"battle_type": 251,
		"raw_args": "fb00"
	},
	{
		"label": 6968,
		"opcode": "BATTLE",
		"flag": 1,
		"fixed_param": [
			272
		],
		"battle_type": 110,
		"raw_args": "6e00"
	},
	{
		"label": 6976,
		"opcode": "WAIT",
		"flag": 1,
		"fixed_param": [
			275
		],
		"raw_args": "5400"
	},
	{
		"label": 6984,
		"opcode": "BATTLE",
		"flag": 1,
		"fixed_param": [
			278
		],
		"battle_type": 113,
		"raw_args": "71003100"
	},
	{
		"label": 6994,
		"opcode": "BATTLE",
		"flag": 1,
		"fixed_param": [
			284
		],
		"battle_type": 100,
		"raw_args": "6400"
	},
	{
		"label": 7002,
		"opcode": "BATTLE",
		"flag": 1,
		"fixed_param": [
			285
		],
		"battle_type": 101,
		"var1": 959,
		"var2": 0,
		"var3": 0,
		"expr": "#6169",
		"msg_jp": "の勝利！",
		"msg_en": " is victorious!",
		"expr2": null,
		"msg_jp2": null,
		"msg_en2": null,
		"expr3": null,
		"msg_jp3": null,
		"msg_en3": null
	},
	{
		"label": 7064,
		"opcode": "BATTLE",
		"flag": 1,
		"fixed_param": [
			288
		],
		"battle_type": 262,
		"raw_args": "0601"
	},
	{
		"label": 7072,
		"opcode": "BATTLE",
		"flag": 1,
		"fixed_param": [
			291
		],
		"battle_type": 3,
		"raw_args": "0300"
	},
	{
		"label": 7080,
		"opcode": "BATTLE",
		"flag": 1,
		"fixed_param": [
			292
		],
		"battle_type": 111,
		"raw_args": "6f00"
	},
	{
		"label": 7088,
		"opcode": "BATTLE",
		"flag": 1,
		"fixed_param": [
			293
		],
		"battle_type": 6,
		"raw_args": "0600"
	},
	{
		"label": 7096,
		"opcode": "EQUN",
		"flag": 1,
		"fixed_param": [
			296
		],
		"raw_args": "07180100"
	},
	{
		"label": 7106,
		"opcode": "EQU",
		"flag": 1,
		"fixed_param": [
			299
		],
		"raw_args": "4a19233634373300"
	},
	{
		"label": 7120,
		"opcode": "EQU",
		"flag": 0,
		"fixed_param": [],
		"raw_args": "4f19233634373800"
	},
	{
		"label": 7132,
		"opcode": "EQU",
		"flag": 0,
		"fixed_param": [],
		"raw_args": "5419233634383300"
	},
	{
		"label": 7144,
		"opcode": "EQU",
		"flag": 0,
		"fixed_param": [],
		"raw_args": "4919233634373200"
	},
	{
		"label": 7156,
		"opcode": "EQU",
		"flag": 0,
		"fixed_param": [],
		"raw_args": "4e19233634373700"
	},
	{
		"label": 7168,
		"opcode": "EQU",
		"flag": 0,
		"fixed_param": [],
		"raw_args": "5319233634383200"
	},
	{
		"label": 7180,
		"opcode": "EQU",
		"flag": 0,
		"fixed_param": [],
		"raw_args": "4819233634373100"
	},
	{
		"label": 7192,
		"opcode": "EQU",
		"flag": 0,
		"fixed_param": [],
		"raw_args": "4d19233634373600"
	},
	{
		"label": 7204,
		"opcode": "EQU",
		"flag": 0,
		"fixed_param": [],
		"raw_args": "5219233634383100"
	},
	{
		"label": 7216,
		"opcode": "EQU",
		"flag": 0,
		"fixed_param": [],
		"raw_args": "4719233634373000"
	},
	{
		"label": 7228,
		"opcode": "EQU",
		"flag": 0,
		"fixed_param": [],
		"raw_args": "4c19233634373500"
	},
	{
		"label": 7240,
		"opcode": "EQU",
		"flag": 0,
		"fixed_param": [],
		"raw_args": "5119233634383000"
	},
	{
		"label": 7252,
		"opcode": "EQU",
		"flag": 1,
		"fixed_param": [
			299
		],
		"raw_args": "4619233631363800"
	},
	{
		"label": 7266,
		"opcode": "EQU",
		"flag": 0,
		"fixed_param": [],
		"raw_args": "4b19233631363900"
	},
	{
		"label": 7278,
		"opcode": "EQU",
		"flag": 0,
		"fixed_param": [],
		"raw_args": "5019233631353100"
	},
	{
		"label": 7290,
		"opcode": "EQUN",
		"flag": 1,
		"fixed_param": [
			302
		],
		"raw_args": "08180000"
	},
	{
		"label": 7300,
		"opcode": "BATTLE",
		"flag": 1,
		"fixed_param": [
			320
		],
		"battle_type": 65535,
		"raw_args": "ffff"
	},
	{
		"label": 7308,
		"opcode": "WAIT_COUNT",
		"flag": 1,
		"fixed_param": [
			329
		],
		"raw_args": "0c00"
	},
	{
		"label": 7316,
		"opcode": "EQUN",
		"flag": 1,
		"fixed_param": [
			348
		],
		"raw_args": "97650000"
	},
	{
		"label": 7326,
		"opcode": "EQUN",
		"flag": 1,
		"fixed_param": [
			349
		],
		"raw_args": "97650000"
	},
	{
		"label": 7336,
		"opcode": "CLOSE_WINDOW",
		"flag": 1,
		"fixed_param": [
			356
		],
		"raw_args": ""
	},
	{
		"label": 7337,
		"opcode": "INIT",
		"flag": 0,
		"fixed_param": [],
		"raw_args": "01ff"
	},
	{
		"label": 7338,
		"opcode": "IMAGELOAD",
		"flag": 0,
		"fixed_param": [],
		"mode": 0,
		"image_id": 65001,
		"var1": null,
		"pos_x": null,
		"pos_y": null,
		"end": null
	},
	{
		"label": 7339,
		"opcode": "DRAW",
		"flag": 0,
		"fixed_param": [],
		"raw_args": "1400"
	},
	{
		"label": 7340,
		"opcode": "WAIT",
		"flag": 0,
		"fixed_param": [],
		"raw_args": ""
	},
	{
		"label": 7341,
		"opcode": "CLOSE_WINDOW",
		"flag": 1,
		"fixed_param": [
			94
		],
		"raw_args": ""
	},
	{
		"label": 7342,
		"opcode": "TASK",
		"flag": 0,
		"fixed_param": [],
		"task_type": 23,
		"raw_args": "1700233631363800233631363900233631353200"
	},
	{
		"label": 7366,
		"opcode": "BGM",
		"flag": 1,
		"fixed_param": [
			359
		],
		"raw_args": "000000003000"
	},
	{
		"label": 7378,
		"opcode": "WAIT_COUNT",
		"flag": 1,
		"fixed_param": [
			362
		],
		"raw_args": "3c00"
	},
	{
		"label": 7386,
		"opcode": "EQU",
		"flag": 1,
		"fixed_param": [
			369
		],
		"raw_args": "7517233631353100"
	},
	{
		"label": 7400,
		"opcode": "EQUN",
		"flag": 1,
		"fixed_param": [
			370
		],
		"raw_args": "01000100"
	},
	{
		"label": 7410,
		"opcode": "FARRETURN",
		"flag": 1,
		"fixed_param": [
			372
		],
		"raw_args": ""
	},
	{
		"label": 7416,
		"opcode": "END",
		"flag": 3,
		"fixed_param": [
			373,
			32768
		],
		"raw_args": ""
	}
]
